arbache_authentication/__init__.py
arbache_authentication/authentication.py
arbache_authentication/tests/__init__.py
arbache_authentication/tests/mocks/__init__.py
arbache_authentication/tests/mocks/authentication.py
arbache_authentication/tests/test_authentication.py
arbache_authentication-1.0.5.dist-info/WHEEL
arbache_authentication-1.0.5.dist-info/METADATA
arbache_authentication-1.0.5.dist-info/RECORD
