Metadata-Version: 2.1
Name: arbache-authentication
Version: 1.0.5
Summary: Pacote de autenticações das aplicações Arbache
Author: Willames
Author-email: williames@arbache.com
Requires-Python: >=3.10.4,<4.0.0
Classifier: Programming Language :: Python :: 3
Requires-Dist: Django (>=4.0.0,<5.0.0)
Requires-Dist: djangorestframework (>=3.13.1,<4.0.0)
Requires-Dist: requests (>=2.27.1,<3.0.0)
